napari_synaptogram/__init__.py
napari_synaptogram/_reader.py
napari_synaptogram/_version.py
napari_synaptogram/_widget.py
napari_synaptogram/_writer.py
napari_synaptogram/napari.yaml
napari_synaptogram-0.0.3.dist-info/licenses/LICENSE
napari_synaptogram-0.0.3.dist-info/METADATA
napari_synaptogram-0.0.3.dist-info/WHEEL
napari_synaptogram-0.0.3.dist-info/entry_points.txt
napari_synaptogram-0.0.3.dist-info/top_level.txt
napari_synaptogram-0.0.3.dist-info/RECORD
