Metadata-Version: 2.4
Name: napari-synaptogram
Version: 0.0.3
Summary: Evaluate synapse ribbon counts in confocal data
Author: Brad Buran
Author-email: buran@ohsu.edu
License: 
Project-URL: Bug Tracker, https://github.com/bburan/napari-synaptogram/issues
Project-URL: Documentation, https://github.com/bburan/napari-synaptogram#README.md
Project-URL: Source Code, https://github.com/bburan/napari-synaptogram
Project-URL: User Support, https://github.com/bburan/napari-synaptogram/issues
Classifier: Development Status :: 2 - Pre-Alpha
Classifier: Framework :: napari
Classifier: Intended Audience :: Developers
Classifier: License :: OSI Approved :: MIT License
Classifier: Operating System :: OS Independent
Classifier: Programming Language :: Python
Classifier: Programming Language :: Python :: 3
Classifier: Programming Language :: Python :: 3 :: Only
Classifier: Programming Language :: Python :: 3.10
Classifier: Programming Language :: Python :: 3.11
Classifier: Programming Language :: Python :: 3.12
Classifier: Programming Language :: Python :: 3.13
Classifier: Topic :: Scientific/Engineering :: Image Processing
Requires-Python: >=3.10
License-File: LICENSE
Requires-Dist: numpy
Requires-Dist: magicgui
Requires-Dist: qtpy
Requires-Dist: scikit-image
Requires-Dist: synaptogram>=0.0.11
Requires-Dist: cochleogram[czi]>=0.10.2
Provides-Extra: all
Requires-Dist: napari[all]; extra == "all"
Dynamic: license-file
